arcwright/__init__.py
arcwright/__main__.py
arcwright/_version.py
arcwright/arcwright.py
arcwright/cli.py
arcwright-0.2.1.dist-info/METADATA
arcwright-0.2.1.dist-info/WHEEL
arcwright-0.2.1.dist-info/entry_points.txt
arcwright-0.2.1.dist-info/licenses/LICENSE
arcwright-0.2.1.dist-info/RECORD
