Metadata-Version: 2.1
Name: arcwright
Version: 0.2.1
Summary: Tools for integrating data from the XPDF-ARC detector on I15-1
Project-URL: Homepage, https://github.com/DiamondLightSource/arcwright
Project-URL: Issues, https://github.com/DiamondLightSource/arcwright/issues
Author-email: Phil Chater <philip.chater@diamond.ac.uk>
Maintainer-email: Dean Keeble <dean.keeble@diamond.ac.uk>
Keywords: arcwright
Classifier: Programming Language :: Python :: 3.10
Classifier: Programming Language :: Python :: 3.9
Requires-Dist: numpy
Requires-Dist: pyfai
Requires-Dist: pyopencl
Requires-Dist: scipy
